MANIFEST.in
README.rst
setup.cfg
setup.py
zeelalchemy/__init__.py
zeelalchemy/classes.py
zeelalchemy/constants.py
zeelalchemy/errors.py
zeelalchemy/utils.py
zeelalchemy.egg-info/PKG-INFO
zeelalchemy.egg-info/SOURCES.txt
zeelalchemy.egg-info/dependency_links.txt
zeelalchemy.egg-info/not-zip-safe
zeelalchemy.egg-info/requires.txt
zeelalchemy.egg-info/top_level.txt
zeelalchemy/tests/__init__.py
zeelalchemy/tests/test_asdict.py
zeelalchemy/tests/test_fromdict.py
zeelalchemy/tests/test_utils.py