Metadata-Version: 1.1
Name: zeelalchemy
Version: 0.1.2.7
Summary: Contains asdict and fromdict methods for SQL-Alchemy declarative models
Home-page: https://github.com/zeel-dev/zeelalchemy
Author: Zeel Network, Inc.
Author-email: hosting@zeel.com
License: MIT
Platform: any
Classifier: Development Status :: 4 - Beta
Classifier: License :: OSI Approved :: MIT License
Classifier: Environment :: Web Environment
Classifier: Intended Audience :: Developers
Classifier: Operating System :: OS Independent
Classifier: Programming Language :: Python
Classifier: Topic :: Internet :: WWW/HTTP :: Dynamic Content
Classifier: Topic :: Software Development :: Libraries :: Python Modules
